zoosync/__init__.py
zoosync/lock.py
zoosync/pool.py
zoosync/queue.py
zoosync/zoosync_core.cpython-313-aarch64-linux-gnu.so
zoosyncmp-2026.1.24.dist-info/METADATA
zoosyncmp-2026.1.24.dist-info/WHEEL
zoosyncmp-2026.1.24.dist-info/RECORD
