Metadata-Version: 2.4
Name: zoosyncmp
Version: 2026.1.24
Requires-Dist: psutil>=7.2.1
Summary: High-performance multiprocessing primitives for Python, written in Rust core.
Requires-Python: >=3.10
